mavlink_tools/configurator/__init__.py
mavlink_tools/configurator/mavlink_params.py
mavlink_tools/configurator/vehicle.py
mavlink_tools/log_analyzer/__init__.py
mavlink_tools/log_analyzer/airspeed.py
mavlink_tools/log_analyzer/altitude.py
mavlink_tools/log_analyzer/color_logging.py
mavlink_tools/log_analyzer/device_id_parser.py
mavlink_tools/log_analyzer/esc_status.py
mavlink_tools/log_analyzer/extract.py
mavlink_tools/log_analyzer/flight_distance.py
mavlink_tools/log_analyzer/ice.py
mavlink_tools/log_analyzer/uorb_topics.py
mavlink_tools/log_analyzer/utils.py
mavlink_tools-0.0.8.dist-info/LICENSE
mavlink_tools-0.0.8.dist-info/METADATA
mavlink_tools-0.0.8.dist-info/WHEEL
mavlink_tools-0.0.8.dist-info/top_level.txt
mavlink_tools-0.0.8.dist-info/RECORD
