Metadata-Version: 2.1
Name: mavlink-tools
Version: 0.0.8
Summary: PX4/ArduPilot MAVLink usefull tools
Author-email: Dmitry Ponomarev <PonomarevDA96@gmail.com>
Project-URL: Homepage, https://github.com/pypa/sampleproject
Project-URL: Bug Tracker, https://github.com/pypa/sampleproject/issues
Classifier: Programming Language :: Python :: 3
Classifier: License :: OSI Approved :: MIT License
Classifier: Operating System :: OS Independent
Requires-Python: >=3.7
License-File: LICENSE
Requires-Dist: matplotlib
Requires-Dist: pytest
Requires-Dist: pyyaml
Requires-Dist: pyserial
Requires-Dist: pymavlink
